{"info": {"id": "1.187854116", "eventId": "30918172", "eventName": "Over/Under 4.5 Goals", "marketType": "OVER_UNDER_45", "openDate": 1632162740169, "name": "Frosinone v Brescia", "numberOfActiveRunner": 2, "countryCode": "", "sport": "TENNIS", "venue": "", "winner": {"id": 1222347, "name": "Under 4.5 Goals", "status": "WINNER", "position": 1}, "delay": 5}, "runners": [{"id": 1222347, "name": "Under 4.5 Goals", "status": "WINNER", "position": 1, "inPlayOdds": 1.12, "inPlayTime": 1632162920207, "avgPrematch": 1.14, "closedOdds": 1.06, "maxPrematch": 1.15, "minPrematch": 1.13, "maxInPlay": 1.95, "minInPlay": 1.01, "inPlayIndex": 6, "lengthOdds": 84, "lengthOddsPrematch": 6, "lengthOddsInPlay": 78}, {"id": 1222346, "name": "Over 4.5 Goals", "status": "LOSER", "position": 2, "inPlayOdds": 9.2, "inPlayTime": 1632163100218, "avgPrematch": 7.9, "closedOdds": 11.0, "maxPrematch": 8.0, "minPrematch": 7.8, "maxInPlay": 55.0, "minInPlay": 2.04, "inPlayIndex": 2, "lengthOdds": 76, "lengthOddsPrematch": 2, "lengthOddsInPlay": 74}], "marketUpdates": [{"timestamp": 1632044418088000000, "openDate": "2021-09-20T18:30:00.000Z", "status": "OPEN", "betDelay": 0, "inPlay": false, "complete": true}, {"timestamp": 1632162740169000000, "openDate": "2021-09-20T18:31:28.000Z", "status": "OPEN", "betDelay": 5, "inPlay": true, "complete": true}, {"timestamp": 1632163751643000000, "openDate": "2021-09-20T18:31:28.000Z", "status": "SUSPENDED", "betDelay": 5, "inPlay": true, "complete": true}, {"timestamp": 1632163820212000000, "openDate": "2021-09-20T18:31:28.000Z", "status": "OPEN", "betDelay": 5, "inPlay": true, "complete": true}, {"timestamp": 1632169549725000000, "openDate": "2021-09-20T18:31:28.000Z", "status": "SUSPENDED", "betDelay": 5, "inPlay": true, "complete": true}, {"timestamp": 1632169639853000000, "openDate": "2021-09-20T18:31:28.000Z", "status": "CLOSED", "betDelay": 5, "inPlay": true, "complete": true}], "odds": [{"runnerId": 1222347, "odds": [{"timestamp": 1632145777927, "ltp": 1.15}, {"timestamp": 1632159429846, "ltp": 1.13}, {"timestamp": 1632160455992, "ltp": 1.15}, {"timestamp": 1632162260060, "ltp": 1.14}, {"timestamp": 1632162438513, "ltp": 1.15}, {"timestamp": 1632162559311, "ltp": 1.14}, {"timestamp": 1632162920207, "ltp": 1.12}, {"timestamp": 1632163220160, "ltp": 1.1}, {"timestamp": 1632163400149, "ltp": 1.24}, {"timestamp": 1632163460198, "ltp": 1.28}, {"timestamp": 1632163520240, "ltp": 1.29}, {"timestamp": 1632163580259, "ltp": 1.3}, {"timestamp": 1632163640220, "ltp": 1.28}, {"timestamp": 1632163751643, "ltp": 1.27}, {"timestamp": 1632163880227, "ltp": 1.24}, {"timestamp": 1632164240203, "ltp": 1.23}, {"timestamp": 1632164300080, "ltp": 1.22}, {"timestamp": 1632164540161, "ltp": 1.19}, {"timestamp": 1632164600228, "ltp": 1.18}, {"timestamp": 1632164660238, "ltp": 1.39}, {"timestamp": 1632164780017, "ltp": 1.18}, {"timestamp": 1632164840188, "ltp": 1.14}, {"timestamp": 1632164900260, "ltp": 1.13}, {"timestamp": 1632164960225, "ltp": 1.14}, {"timestamp": 1632165020205, "ltp": 1.31}, {"timestamp": 1632165080251, "ltp": 1.34}, {"timestamp": 1632165200084, "ltp": 1.32}, {"timestamp": 1632165260191, "ltp": 1.31}, {"timestamp": 1632165379866, "ltp": 1.88}, {"timestamp": 1632165440258, "ltp": 1.94}, {"timestamp": 1632165500223, "ltp": 1.95}, {"timestamp": 1632165560128, "ltp": 1.92}, {"timestamp": 1632165620067, "ltp": 1.91}, {"timestamp": 1632165679993, "ltp": 1.87}, {"timestamp": 1632165739991, "ltp": 1.89}, {"timestamp": 1632165860258, "ltp": 1.87}, {"timestamp": 1632165919519, "ltp": 1.88}, {"timestamp": 1632165979803, "ltp": 1.89}, {"timestamp": 1632166160074, "ltp": 1.9}, {"timestamp": 1632166339813, "ltp": 1.91}, {"timestamp": 1632166399253, "ltp": 1.89}, {"timestamp": 1632166519816, "ltp": 1.91}, {"timestamp": 1632166580169, "ltp": 1.88}, {"timestamp": 1632166640262, "ltp": 1.84}, {"timestamp": 1632166700080, "ltp": 1.81}, {"timestamp": 1632166760149, "ltp": 1.8}, {"timestamp": 1632166820251, "ltp": 1.73}, {"timestamp": 1632166880176, "ltp": 1.72}, {"timestamp": 1632166940216, "ltp": 1.7}, {"timestamp": 1632167060185, "ltp": 1.62}, {"timestamp": 1632167120190, "ltp": 1.59}, {"timestamp": 1632167180180, "ltp": 1.54}, {"timestamp": 1632167240226, "ltp": 1.53}, {"timestamp": 1632167300234, "ltp": 1.51}, {"timestamp": 1632167360255, "ltp": 1.47}, {"timestamp": 1632167420204, "ltp": 1.43}, {"timestamp": 1632167480195, "ltp": 1.42}, {"timestamp": 1632167540213, "ltp": 1.38}, {"timestamp": 1632167660191, "ltp": 1.37}, {"timestamp": 1632167720063, "ltp": 1.33}, {"timestamp": 1632167780083, "ltp": 1.3}, {"timestamp": 1632167899974, "ltp": 1.27}, {"timestamp": 1632167960243, "ltp": 1.26}, {"timestamp": 1632168020133, "ltp": 1.22}, {"timestamp": 1632168080216, "ltp": 1.21}, {"timestamp": 1632168140067, "ltp": 1.2}, {"timestamp": 1632168200065, "ltp": 1.18}, {"timestamp": 1632168260224, "ltp": 1.17}, {"timestamp": 1632168320243, "ltp": 1.15}, {"timestamp": 1632168440173, "ltp": 1.13}, {"timestamp": 1632168560174, "ltp": 1.12}, {"timestamp": 1632168620163, "ltp": 1.11}, {"timestamp": 1632168680241, "ltp": 1.09}, {"timestamp": 1632168740219, "ltp": 1.08}, {"timestamp": 1632168860066, "ltp": 1.06}, {"timestamp": 1632168920117, "ltp": 1.04}, {"timestamp": 1632168980203, "ltp": 1.03}, {"timestamp": 1632169100075, "ltp": 1.01}, {"timestamp": 1632169220248, "ltp": 1.02}, {"timestamp": 1632169280159, "ltp": 1.16}, {"timestamp": 1632169400013, "ltp": 1.13}, {"timestamp": 1632169460172, "ltp": 1.1}, {"timestamp": 1632169520223, "ltp": 1.14}, {"timestamp": 1632169549725, "ltp": 1.06}]}, {"runnerId": 1222346, "odds": [{"timestamp": 1632160637976, "ltp": 7.8}, {"timestamp": 1632162620211, "ltp": 8.0}, {"timestamp": 1632163100218, "ltp": 9.2}, {"timestamp": 1632163400149, "ltp": 11.0}, {"timestamp": 1632163460198, "ltp": 4.1}, {"timestamp": 1632163520240, "ltp": 4.4}, {"timestamp": 1632163580259, "ltp": 4.3}, {"timestamp": 1632163640220, "ltp": 4.2}, {"timestamp": 1632163700059, "ltp": 4.6}, {"timestamp": 1632163751643, "ltp": 4.7}, {"timestamp": 1632163880227, "ltp": 5.0}, {"timestamp": 1632163940091, "ltp": 4.9}, {"timestamp": 1632164060232, "ltp": 5.2}, {"timestamp": 1632164180207, "ltp": 5.3}, {"timestamp": 1632164300080, "ltp": 5.4}, {"timestamp": 1632164660238, "ltp": 6.8}, {"timestamp": 1632164780017, "ltp": 6.6}, {"timestamp": 1632164840188, "ltp": 8.0}, {"timestamp": 1632164900260, "ltp": 8.4}, {"timestamp": 1632164960225, "ltp": 8.6}, {"timestamp": 1632165200084, "ltp": 3.85}, {"timestamp": 1632165260191, "ltp": 4.3}, {"timestamp": 1632165379866, "ltp": 2.14}, {"timestamp": 1632165440258, "ltp": 2.06}, {"timestamp": 1632165500223, "ltp": 2.04}, {"timestamp": 1632165560128, "ltp": 2.14}, {"timestamp": 1632165620067, "ltp": 2.1}, {"timestamp": 1632165739991, "ltp": 2.14}, {"timestamp": 1632165800202, "ltp": 2.12}, {"timestamp": 1632165919519, "ltp": 2.14}, {"timestamp": 1632165979803, "ltp": 2.1}, {"timestamp": 1632166160074, "ltp": 2.08}, {"timestamp": 1632166219203, "ltp": 2.12}, {"timestamp": 1632166459038, "ltp": 2.1}, {"timestamp": 1632166580169, "ltp": 2.14}, {"timestamp": 1632166640262, "ltp": 2.18}, {"timestamp": 1632166700080, "ltp": 2.2}, {"timestamp": 1632166760149, "ltp": 2.28}, {"timestamp": 1632166820251, "ltp": 2.32}, {"timestamp": 1632166880176, "ltp": 2.42}, {"timestamp": 1632167000199, "ltp": 2.58}, {"timestamp": 1632167060185, "ltp": 2.68}, {"timestamp": 1632167120190, "ltp": 2.72}, {"timestamp": 1632167180180, "ltp": 2.76}, {"timestamp": 1632167240226, "ltp": 2.9}, {"timestamp": 1632167300234, "ltp": 3.0}, {"timestamp": 1632167360255, "ltp": 3.05}, {"timestamp": 1632167420204, "ltp": 3.25}, {"timestamp": 1632167480195, "ltp": 3.5}, {"timestamp": 1632167540213, "ltp": 3.6}, {"timestamp": 1632167600199, "ltp": 3.7}, {"timestamp": 1632167720063, "ltp": 4.0}, {"timestamp": 1632167780083, "ltp": 4.1}, {"timestamp": 1632167840160, "ltp": 4.3}, {"timestamp": 1632167899974, "ltp": 4.7}, {"timestamp": 1632167960243, "ltp": 4.8}, {"timestamp": 1632168020133, "ltp": 5.3}, {"timestamp": 1632168080216, "ltp": 5.7}, {"timestamp": 1632168140067, "ltp": 6.0}, {"timestamp": 1632168200065, "ltp": 6.4}, {"timestamp": 1632168260224, "ltp": 7.0}, {"timestamp": 1632168320243, "ltp": 7.2}, {"timestamp": 1632168440173, "ltp": 8.2}, {"timestamp": 1632168620163, "ltp": 9.2}, {"timestamp": 1632168680241, "ltp": 12.0}, {"timestamp": 1632168800208, "ltp": 15.5}, {"timestamp": 1632168860066, "ltp": 21.0}, {"timestamp": 1632168980203, "ltp": 24.0}, {"timestamp": 1632169100075, "ltp": 36.0}, {"timestamp": 1632169160218, "ltp": 55.0}, {"timestamp": 1632169220248, "ltp": 50.0}, {"timestamp": 1632169280159, "ltp": 6.8}, {"timestamp": 1632169340230, "ltp": 7.2}, {"timestamp": 1632169400013, "ltp": 8.6}, {"timestamp": 1632169460172, "ltp": 9.6}, {"timestamp": 1632169520223, "ltp": 11.0}]}]}