{"info": {"id": "1.187475506", "eventId": "30887299", "eventName": "R2 6f Mdn Claim", "marketType": "WIN", "openDate": 1631309192811, "name": "Woodbine (US) 10th Sep", "numberOfActiveRunner": 13, "countryCode": "", "sport": "HORSE RACING", "venue": "", "winner": {"id": 40869114, "name": "Musical Reload", "status": "WINNER", "position": 9}, "delay": 1}, "runners": [{"id": 40869115, "name": "Its A Birdie", "status": "REMOVED", "position": 1, "inPlayOdds": 0, "openOdds": 0, "closedOdds": 0, "maxPrematch": 0, "minPrematch": 0, "maxInPlay": 0, "minInPlay": 0}, {"id": 39304699, "name": "Sassywithattitude", "status": "LOSER", "position": 2, "inPlayOdds": 15.5, "inPlayTime": 1631309192811, "avgPrematch": 21.43, "closedOdds": 400.0, "maxPrematch": 26.0, "minPrematch": 18.5, "maxInPlay": 400.0, "minInPlay": 15.5, "inPlayIndex": 7, "lengthOdds": 9, "lengthOddsPrematch": 7, "lengthOddsInPlay": 2}, {"id": 39914177, "name": "Zafeather", "status": "LOSER", "position": 3, "inPlayOdds": 910.0, "inPlayTime": 1631309249776, "avgPrematch": 31.75, "closedOdds": 910.0, "maxPrematch": 38.0, "minPrematch": 25.0, "maxInPlay": 910.0, "minInPlay": 910.0, "inPlayIndex": 8, "lengthOdds": 9, "lengthOddsPrematch": 8, "lengthOddsInPlay": 1}, {"id": 40475075, "name": "Devil In Her Heart", "status": "LOSER", "position": 4, "inPlayOdds": 13.0, "inPlayTime": 1631309192811, "avgPrematch": 14.46, "closedOdds": 690.0, "maxPrematch": 17.0, "minPrematch": 12.0, "maxInPlay": 690.0, "minInPlay": 13.0, "inPlayIndex": 12, "lengthOdds": 14, "lengthOddsPrematch": 12, "lengthOddsInPlay": 2}, {"id": 40869116, "name": "Princess Lavender", "status": "LOSER", "position": 5, "inPlayOdds": 330.0, "inPlayTime": 1631309192811, "avgPrematch": 56.44, "closedOdds": 1000.0, "maxPrematch": 70.0, "minPrematch": 36.0, "maxInPlay": 1000.0, "minInPlay": 330.0, "inPlayIndex": 9, "lengthOdds": 11, "lengthOddsPrematch": 9, "lengthOddsInPlay": 2}, {"id": 40869112, "name": "Queen Cashmere", "status": "LOSER", "position": 6, "inPlayOdds": 4.0, "inPlayTime": 1631309192811, "avgPrematch": 5.13, "closedOdds": 26.0, "maxPrematch": 7.2, "minPrematch": 3.6, "maxInPlay": 26.0, "minInPlay": 4.0, "inPlayIndex": 13, "lengthOdds": 15, "lengthOddsPrematch": 13, "lengthOddsInPlay": 2}, {"id": 11422657, "name": "Weve Had Enough", "status": "LOSER", "position": 7, "inPlayOdds": 50.0, "inPlayTime": 1631309192811, "avgPrematch": 7.24, "closedOdds": 690.0, "maxPrematch": 9.8, "minPrematch": 5.1, "maxInPlay": 690.0, "minInPlay": 50.0, "inPlayIndex": 14, "lengthOdds": 16, "lengthOddsPrematch": 14, "lengthOddsInPlay": 2}, {"id": 40627298, "name": "Carlas Honor", "status": "LOSER", "position": 8, "inPlayOdds": 28.0, "inPlayTime": 1631309192811, "avgPrematch": 17.79, "closedOdds": 690.0, "maxPrematch": 24.0, "minPrematch": 14.5, "maxInPlay": 690.0, "minInPlay": 28.0, "inPlayIndex": 7, "lengthOdds": 9, "lengthOddsPrematch": 7, "lengthOddsInPlay": 2}, {"id": 40869114, "name": "Musical Reload", "status": "WINNER", "position": 9, "inPlayOdds": 3.25, "inPlayTime": 1631309192811, "avgPrematch": 5.77, "closedOdds": 1.01, "maxPrematch": 8.2, "minPrematch": 4.8, "maxInPlay": 3.25, "minInPlay": 1.01, "inPlayIndex": 13, "lengthOdds": 15, "lengthOddsPrematch": 13, "lengthOddsInPlay": 2}, {"id": 40869113, "name": "Original Me", "status": "LOSER", "position": 10, "inPlayOdds": 90.0, "inPlayTime": 1631309192811, "avgPrematch": 40.4, "closedOdds": 950.0, "maxPrematch": 50.0, "minPrematch": 28.0, "maxInPlay": 950.0, "minInPlay": 90.0, "inPlayIndex": 5, "lengthOdds": 7, "lengthOddsPrematch": 5, "lengthOddsInPlay": 2}, {"id": 40132249, "name": "Thanks Laura", "status": "LOSER", "position": 11, "inPlayOdds": 6.0, "inPlayTime": 1631309192811, "avgPrematch": 4.83, "closedOdds": 690.0, "maxPrematch": 6.6, "minPrematch": 3.26, "maxInPlay": 690.0, "minInPlay": 6.0, "inPlayIndex": 17, "lengthOdds": 19, "lengthOddsPrematch": 17, "lengthOddsInPlay": 2}, {"id": 40132252, "name": "Call Me Kitty", "status": "LOSER", "position": 12, "inPlayOdds": 38.0, "inPlayTime": 1631309192811, "avgPrematch": 21.77, "closedOdds": 1000.0, "maxPrematch": 29.0, "minPrematch": 14.0, "maxInPlay": 1000.0, "minInPlay": 38.0, "inPlayIndex": 15, "lengthOdds": 17, "lengthOddsPrematch": 15, "lengthOddsInPlay": 2}, {"id": 3766935, "name": "Tarantula", "status": "LOSER", "position": 13, "inPlayOdds": 170.0, "inPlayTime": 1631309192811, "avgPrematch": 78.48, "closedOdds": 940.0, "maxPrematch": 200.0, "minPrematch": 8.26, "maxInPlay": 940.0, "minInPlay": 170.0, "inPlayIndex": 15, "lengthOdds": 17, "lengthOddsPrematch": 15, "lengthOddsInPlay": 2}], "marketUpdates": [{"timestamp": 1631208035977000000, "openDate": "2021-09-10T20:50:00.000Z", "status": "OPEN", "betDelay": 0, "inPlay": false, "complete": true}, {"timestamp": 1631309192811000000, "openDate": "2021-09-10T20:50:00.000Z", "status": "OPEN", "betDelay": 1, "inPlay": true, "complete": true}, {"timestamp": 1631309249776000000, "openDate": "2021-09-10T20:50:00.000Z", "status": "SUSPENDED", "betDelay": 1, "inPlay": true, "complete": true}, {"timestamp": 1631309552837000000, "openDate": "2021-09-10T20:50:00.000Z", "status": "CLOSED", "betDelay": 1, "inPlay": true, "complete": true}], "odds": [{"runnerId": 40869115, "odds": []}, {"runnerId": 39304699, "odds": [{"timestamp": 1631308592801, "ltp": 18.5}, {"timestamp": 1631308832844, "ltp": 20.0}, {"timestamp": 1631308892953, "ltp": 22.0}, {"timestamp": 1631308952896, "ltp": 26.0}, {"timestamp": 1631309012839, "ltp": 25.0}, {"timestamp": 1631309072901, "ltp": 18.5}, {"timestamp": 1631309132788, "ltp": 20.0}, {"timestamp": 1631309192811, "ltp": 15.5}, {"timestamp": 1631309249776, "ltp": 400.0}]}, {"runnerId": 39914177, "odds": [{"timestamp": 1631308652873, "ltp": 25.0}, {"timestamp": 1631308772949, "ltp": 29.0}, {"timestamp": 1631308832844, "ltp": 34.0}, {"timestamp": 1631308892953, "ltp": 30.0}, {"timestamp": 1631308952896, "ltp": 32.0}, {"timestamp": 1631309012839, "ltp": 30.0}, {"timestamp": 1631309072901, "ltp": 38.0}, {"timestamp": 1631309132788, "ltp": 36.0}, {"timestamp": 1631309249776, "ltp": 910.0}]}, {"runnerId": 40475075, "odds": [{"timestamp": 1631308226336, "ltp": 12.5}, {"timestamp": 1631308412882, "ltp": 13.5}, {"timestamp": 1631308472797, "ltp": 14.5}, {"timestamp": 1631308652873, "ltp": 15.5}, {"timestamp": 1631308712784, "ltp": 17.0}, {"timestamp": 1631308772949, "ltp": 14.5}, {"timestamp": 1631308832844, "ltp": 15.5}, {"timestamp": 1631308892953, "ltp": 17.0}, {"timestamp": 1631308952896, "ltp": 15.5}, {"timestamp": 1631309012839, "ltp": 13.5}, {"timestamp": 1631309072901, "ltp": 12.5}, {"timestamp": 1631309132788, "ltp": 12.0}, {"timestamp": 1631309192811, "ltp": 13.0}, {"timestamp": 1631309249776, "ltp": 690.0}]}, {"runnerId": 40869116, "odds": [{"timestamp": 1631308412882, "ltp": 36.0}, {"timestamp": 1631308472797, "ltp": 44.0}, {"timestamp": 1631308652873, "ltp": 55.0}, {"timestamp": 1631308772949, "ltp": 70.0}, {"timestamp": 1631308832844, "ltp": 48.0}, {"timestamp": 1631308952896, "ltp": 65.0}, {"timestamp": 1631309012839, "ltp": 70.0}, {"timestamp": 1631309072901, "ltp": 50.0}, {"timestamp": 1631309132788, "ltp": 70.0}, {"timestamp": 1631309192811, "ltp": 330.0}, {"timestamp": 1631309249776, "ltp": 1000.0}]}, {"runnerId": 40869112, "odds": [{"timestamp": 1631308112778, "ltp": 7.2}, {"timestamp": 1631308226336, "ltp": 7.0}, {"timestamp": 1631308292431, "ltp": 6.2}, {"timestamp": 1631308472797, "ltp": 6.4}, {"timestamp": 1631308592801, "ltp": 6.0}, {"timestamp": 1631308652873, "ltp": 5.5}, {"timestamp": 1631308712784, "ltp": 4.8}, {"timestamp": 1631308772949, "ltp": 4.5}, {"timestamp": 1631308832844, "ltp": 4.1}, {"timestamp": 1631308952896, "ltp": 3.9}, {"timestamp": 1631309012839, "ltp": 3.75}, {"timestamp": 1631309072901, "ltp": 3.6}, {"timestamp": 1631309132788, "ltp": 3.8}, {"timestamp": 1631309192811, "ltp": 4.0}, {"timestamp": 1631309249776, "ltp": 26.0}]}, {"runnerId": 11422657, "odds": [{"timestamp": 1631308172078, "ltp": 5.2}, {"timestamp": 1631308292431, "ltp": 5.1}, {"timestamp": 1631308352021, "ltp": 5.5}, {"timestamp": 1631308412882, "ltp": 5.8}, {"timestamp": 1631308472797, "ltp": 6.0}, {"timestamp": 1631308592801, "ltp": 7.4}, {"timestamp": 1631308652873, "ltp": 6.8}, {"timestamp": 1631308712784, "ltp": 7.0}, {"timestamp": 1631308772949, "ltp": 7.4}, {"timestamp": 1631308832844, "ltp": 8.8}, {"timestamp": 1631308892953, "ltp": 8.0}, {"timestamp": 1631309012839, "ltp": 9.0}, {"timestamp": 1631309072901, "ltp": 9.6}, {"timestamp": 1631309132788, "ltp": 9.8}, {"timestamp": 1631309192811, "ltp": 50.0}, {"timestamp": 1631309249776, "ltp": 690.0}]}, {"runnerId": 40627298, "odds": [{"timestamp": 1631308652873, "ltp": 14.5}, {"timestamp": 1631308772949, "ltp": 15.5}, {"timestamp": 1631308832844, "ltp": 14.5}, {"timestamp": 1631308892953, "ltp": 16.5}, {"timestamp": 1631308952896, "ltp": 17.5}, {"timestamp": 1631309012839, "ltp": 22.0}, {"timestamp": 1631309132788, "ltp": 24.0}, {"timestamp": 1631309192811, "ltp": 28.0}, {"timestamp": 1631309249776, "ltp": 690.0}]}, {"runnerId": 40869114, "odds": [{"timestamp": 1631308412882, "ltp": 8.2}, {"timestamp": 1631308472797, "ltp": 6.2}, {"timestamp": 1631308532849, "ltp": 6.0}, {"timestamp": 1631308592801, "ltp": 5.9}, {"timestamp": 1631308652873, "ltp": 6.2}, {"timestamp": 1631308712784, "ltp": 5.8}, {"timestamp": 1631308772949, "ltp": 5.5}, {"timestamp": 1631308832844, "ltp": 5.7}, {"timestamp": 1631308892953, "ltp": 5.4}, {"timestamp": 1631308952896, "ltp": 5.3}, {"timestamp": 1631309012839, "ltp": 5.1}, {"timestamp": 1631309072901, "ltp": 4.9}, {"timestamp": 1631309132788, "ltp": 4.8}, {"timestamp": 1631309192811, "ltp": 3.25}, {"timestamp": 1631309249776, "ltp": 1.01}]}, {"runnerId": 40869113, "odds": [{"timestamp": 1631308532849, "ltp": 44.0}, {"timestamp": 1631308712784, "ltp": 48.0}, {"timestamp": 1631308772949, "ltp": 50.0}, {"timestamp": 1631308952896, "ltp": 28.0}, {"timestamp": 1631309072901, "ltp": 32.0}, {"timestamp": 1631309192811, "ltp": 90.0}, {"timestamp": 1631309249776, "ltp": 950.0}]}, {"runnerId": 40132249, "odds": [{"timestamp": 1631299587174, "ltp": 3.55}, {"timestamp": 1631301511677, "ltp": 3.26}, {"timestamp": 1631307752901, "ltp": 3.55}, {"timestamp": 1631308051417, "ltp": 3.65}, {"timestamp": 1631308172078, "ltp": 3.6}, {"timestamp": 1631308352021, "ltp": 3.75}, {"timestamp": 1631308472797, "ltp": 4.4}, {"timestamp": 1631308532849, "ltp": 4.5}, {"timestamp": 1631308592801, "ltp": 4.6}, {"timestamp": 1631308652873, "ltp": 4.9}, {"timestamp": 1631308712784, "ltp": 5.4}, {"timestamp": 1631308772949, "ltp": 6.0}, {"timestamp": 1631308832844, "ltp": 6.2}, {"timestamp": 1631308892953, "ltp": 5.9}, {"timestamp": 1631308952896, "ltp": 6.0}, {"timestamp": 1631309072901, "ltp": 6.2}, {"timestamp": 1631309132788, "ltp": 6.6}, {"timestamp": 1631309192811, "ltp": 6.0}, {"timestamp": 1631309249776, "ltp": 690.0}]}, {"runnerId": 40132252, "odds": [{"timestamp": 1631307811362, "ltp": 14.0}, {"timestamp": 1631308172078, "ltp": 17.0}, {"timestamp": 1631308352021, "ltp": 18.0}, {"timestamp": 1631308472797, "ltp": 19.5}, {"timestamp": 1631308532849, "ltp": 17.0}, {"timestamp": 1631308592801, "ltp": 20.0}, {"timestamp": 1631308652873, "ltp": 23.0}, {"timestamp": 1631308712784, "ltp": 24.0}, {"timestamp": 1631308772949, "ltp": 25.0}, {"timestamp": 1631308832844, "ltp": 21.0}, {"timestamp": 1631308892953, "ltp": 20.0}, {"timestamp": 1631308952896, "ltp": 24.0}, {"timestamp": 1631309012839, "ltp": 29.0}, {"timestamp": 1631309072901, "ltp": 28.0}, {"timestamp": 1631309132788, "ltp": 27.0}, {"timestamp": 1631309192811, "ltp": 38.0}, {"timestamp": 1631309249776, "ltp": 1000.0}]}, {"runnerId": 3766935, "odds": [{"timestamp": 1631294637341, "ltp": 9.0}, {"timestamp": 1631301511677, "ltp": 8.26}, {"timestamp": 1631303901163, "ltp": 9.0}, {"timestamp": 1631305050841, "ltp": 20.0}, {"timestamp": 1631307752901, "ltp": 30.0}, {"timestamp": 1631307811362, "ltp": 25.0}, {"timestamp": 1631308352021, "ltp": 36.0}, {"timestamp": 1631308652873, "ltp": 60.0}, {"timestamp": 1631308772949, "ltp": 100.0}, {"timestamp": 1631308832844, "ltp": 140.0}, {"timestamp": 1631308892953, "ltp": 130.0}, {"timestamp": 1631308952896, "ltp": 150.0}, {"timestamp": 1631309012839, "ltp": 200.0}, {"timestamp": 1631309072901, "ltp": 150.0}, {"timestamp": 1631309132788, "ltp": 110.0}, {"timestamp": 1631309192811, "ltp": 170.0}, {"timestamp": 1631309249776, "ltp": 940.0}]}]}